{"nodes":[{"label":"Семён Субботин","x":-867.2015380859375,"y":904.3223266601562,"id":"1","attributes":{"country":"1","bdate":"13.4.1999","Modularity Class":"2","photo_50":"https://pp.userapi.com/c615721/v615721311/6426/0QXSpciX2no.jpg","screen_name":"gogi07","city":"1","sex":"2","last_name":"Субботин","first_name":"Семён","relation":"1"},"color":"rgb(255,82,0)","size":33.589744567871094},{"label":"Lily Osborne","x":350.21826171875,"y":456.18316650390625,"id":"73","attributes":{"country":"0","bdate":"28.9","Modularity Class":"10","photo_50":"https://pp.userapi.com/c830608/v830608220/9e14d/1STPGsR670s.jpg","screen_name":"urmyimagination","city":"0","sex":"1","last_name":"Osborne","first_name":"Lily","relation":"0"},"color":"rgb(79,106,149)","size":48.46154022216797},{"label":"Анастасия Чебанова","x":-1245.847900390625,"y":188.90394592285156,"id":"25","attributes":{"country":"1","bdate":"6.9","Modularity Class":"2","photo_50":"https://pp.userapi.com/c840236/v840236148/52ba8/uXVM29zt1Xk.jpg","screen_name":"savvasaam","city":"1","sex":"1","last_name":"Чебанова","first_name":"Анастасия","relation":"0"},"color":"rgb(255,82,0)","size":33.589744567871094},{"label":"Allen Walker","x":826.5709228515625,"y":-970.4642333984375,"id":"55","attributes":{"country":"49","bdate":"10.9.1992","Modularity Class":"17","photo_50":"https://pp.userapi.com/c831309/v831309133/d6036/iboX2iTXBuo.jpg","screen_name":"id_hitorih","city":"295","sex":"2","last_name":"Walker","first_name":"Allen","relation":"7"},"color":"rgb(0,191,246)","size":31.0256404876709},{"label":"Alina Harwood","x":55.607032775878906,"y":779.0538330078125,"id":"80","attributes":{"country":"1","Modularity Class":"10","photo_50":"https://pp.userapi.com/c638228/v638228139/4cbc1/Ef_tqi62keU.jpg","screen_name":"alinalyapota","city":"1","sex":"1","last_name":"Harwood","first_name":"Alina","relation":"0"},"color":"rgb(79,106,149)","size":44.35897445678711},{"label":"Алёна Викторовна","x":-614.1016845703125,"y":-382.79034423828125,"id":"41","attributes":{"country":"1","bdate":"15.5","Modularity Class":"2","photo_50":"https://pp.userapi.com/c616425/v616425291/c742/URUbT6zNgDE.jpg","screen_name":"id134413291","city":"1","sex":"1","last_name":"Викторовна","first_name":"Алёна","relation":"0"},"color":"rgb(255,82,0)","size":31.0256404876709},{"label":"Dzi Roi","x":-934.1524047851562,"y":-267.26434326171875,"id":"63","attributes":{"country":"1","bdate":"27.9","Modularity Class":"2","photo_50":"https://pp.userapi.com/c830309/v830309304/cfb84/4MpPLyn5ahY.jpg","screen_name":"prosto_sonito","city":"1","sex":"1","last_name":"Roi","first_name":"Dzi","relation":"0"},"color":"rgb(255,82,0)","size":36.66666793823242},{"label":"Тамара Попова","x":-312.0750732421875,"y":-386.19512939453125,"id":"76","attributes":{"country":"1","bdate":"14.5","Modularity Class":"14","photo_50":"https://pp.userapi.com/c621702/v621702982/6eb6d/dcJ4LuwQ-ho.jpg","screen_name":"id319487192","city":"1","sex":"1","last_name":"Попова","first_name":"Тамара"},"color":"rgb(117,119,5)","size":30.0},{"label":"Дарья Куликова","x":440.14300537109375,"y":-249.4080047607422,"id":"77","attributes":{"country":"0","bdate":"1.9","Modularity Class":"15","photo_50":"https://pp.userapi.com/c841231/v841231910/2878e/vB22cjFvrcY.jpg","screen_name":"darkulikova","city":"0","sex":"1","last_name":"Куликова","first_name":"Дарья"},"color":"rgb(176,101,172)","size":30.0},{"label":"Арина Гурина","x":506.98443603515625,"y":257.3477478027344,"id":"69","attributes":{"country":"1","bdate":"26.10","Modularity Class":"10","photo_50":"https://pp.userapi.com/c846520/v846520864/35b82/Grqk9IivA6U.jpg","screen_name":"guari","city":"106","sex":"2","last_name":"Гурина","first_name":"Арина","relation":"0"},"color":"rgb(79,106,149)","size":47.43589782714844},{"label":"Лиля Семёнова","x":1155.0863037109375,"y":-511.74517822265625,"id":"71","attributes":{"country":"1","bdate":"26.5.1999","Modularity Class":"12","photo_50":"https://pp.userapi.com/c621513/v621513083/91659/ldSSwN6h6iw.jpg","screen_name":"idashsev","city":"1","sex":"1","last_name":"Семёнова","first_name":"Лиля","relation":"0"},"color":"rgb(181,96,41)","size":30.0},{"label":"Dana Solomatina","x":-445.24786376953125,"y":625.703369140625,"id":"21","attributes":{"country":"0","bdate":"16.12","Modularity Class":"5","photo_50":"https://pp.userapi.com/c639817/v639817008/21ed7/8E1SkroUn64.jpg","screen_name":"danasolo","city":"0","sex":"1","last_name":"Solomatina","first_name":"Dana","relation":"0"},"color":"rgb(0,174,152)","size":36.153846740722656},{"label":"Александра Нанотехнолог","x":884.30029296875,"y":-465.412841796875,"id":"12","attributes":{"country":"1","bdate":"11.3.1993","Modularity Class":"3","photo_50":"https://pp.userapi.com/c837236/v837236049/9015/m9-85XEU9a8.jpg","screen_name":"pancha_pancha","city":"1","sex":"1","nickname":"Pancha","last_name":"Нанотехнолог","first_name":"Александра"},"color":"rgb(99,139,254)","size":30.0},{"label":"Александр Ташко","x":-411.849853515625,"y":1130.8331298828125,"id":"26","attributes":{"country":"1","Modularity Class":"5","photo_50":"https://pp.userapi.com/c824410/v824410189/3ad4f/oKLCb_xYlas.jpg","screen_name":"id98926123","city":"1","sex":"2","last_name":"Ташко","first_name":"Александр","relation":"0"},"color":"rgb(0,174,152)","size":37.17948913574219},{"label":"Кирилл Коротков","x":-879.5479125976562,"y":487.87115478515625,"id":"5","attributes":{"country":"1","bdate":"19.3.1999","Modularity Class":"2","photo_50":"https://pp.userapi.com/c620730/v620730035/1b207/B7JjVoC_anY.jpg","screen_name":"id41194035","city":"1","sex":"2","last_name":"Коротков","first_name":"Кирилл","relation":"1"},"color":"rgb(255,82,0)","size":38.71794891357422},{"label":"Катя Селиванова","x":581.9135131835938,"y":546.1419677734375,"id":"64","attributes":{"country":"1","bdate":"29.12","Modularity Class":"10","photo_50":"https://pp.userapi.com/c841035/v841035085/5fafa/C9yPmDvcaeM.jpg","screen_name":"just_noone","city":"1","sex":"1","last_name":"Селиванова","first_name":"Катя","relation":"1"},"color":"rgb(79,106,149)","size":46.410255432128906},{"label":"Анна Фадеева","x":968.9380493164062,"y":222.5970458984375,"id":"3","attributes":{"country":"1","bdate":"17.5","Modularity Class":"10","photo_50":"https://pp.userapi.com/c845019/v845019509/1bdc3/FVlgAv3LrAA.jpg","screen_name":"mayskaya_anjuta","city":"1","sex":"1","last_name":"Фадеева","first_name":"Анна","relation":"2"},"color":"rgb(79,106,149)","size":38.20512771606445},{"label":"Александра Матчина","x":-769.3339233398438,"y":152.39022827148438,"id":"15","attributes":{"country":"1","bdate":"13.1","Modularity Class":"2","photo_50":"https://pp.userapi.com/c626224/v626224898/604ff/txRiCH8vxo4.jpg","screen_name":"sandaaaa","city":"1","sex":"1","last_name":"Матчина","first_name":"Александра","relation":"0"},"color":"rgb(255,82,0)","size":38.71794891357422},{"label":"DELETED ","x":-695.3169555664062,"y":-722.4066772460938,"id":"79","attributes":{"Modularity Class":"2","photo_50":"https://vk.com/images/deactivated_50.png","sex":"2","first_name":"DELETED"},"color":"rgb(255,82,0)","size":30.512821197509766},{"label":"Юлия Кузьмина","x":-222.10630798339844,"y":-999.3961181640625,"id":"18","attributes":{"country":"1","bdate":"29.3.1999","Modularity Class":"8","photo_50":"https://pp.userapi.com/c845417/v845417148/34306/eslaPX_-n2s.jpg","screen_name":"xodrst","city":"0","sex":"1","last_name":"Кузьмина","first_name":"Юлия","relation":"0"},"color":"rgb(99,172,0)","size":40.25640869140625},{"label":"Grisha Vatrushkin","x":-1208.2041015625,"y":-319.86480712890625,"id":"78","attributes":{"country":"0","Modularity Class":"2","photo_50":"https://pp.userapi.com/c845324/v845324065/23a1c/_LN_uTIIy_A.jpg","screen_name":"id344985256","city":"0","sex":"2","last_name":"Vatrushkin","first_name":"Grisha"},"color":"rgb(255,82,0)","size":31.538461685180664},{"label":"Анна Пивоварова","x":1243.53662109375,"y":261.0357360839844,"id":"33","attributes":{"country":"1","bdate":"7.11.1999","Modularity Class":"0","photo_50":"https://pp.userapi.com/c638519/v638519051/548d7/g76DdUB-4fE.jpg","screen_name":"id117805402","city":"859","sex":"1","last_name":"Пивоварова","first_name":"Анна","relation":"0"},"color":"rgb(199,131,0)","size":32.0512809753418},{"label":"Женя Пономарева","x":309.8418273925781,"y":-928.2432250976562,"id":"13","attributes":{"country":"1","bdate":"20.1","Modularity Class":"8","photo_50":"https://pp.userapi.com/c840324/v840324730/23ed/OXNdHyjZ7Yg.jpg","screen_name":"id60272453","city":"22","sex":"1","last_name":"Пономарева","first_name":"Женя","relation":"0"},"color":"rgb(99,172,0)","size":39.230770111083984},{"label":"Мария Кожемяк","x":630.56689453125,"y":1080.0474853515625,"id":"51","attributes":{"country":"1","bdate":"26.4.1999","Modularity Class":"10","photo_50":"https://pp.userapi.com/c824601/v824601978/ff71b/5BQTH2U3cFw.jpg","screen_name":"id162420913","city":"1","sex":"1","last_name":"Кожемяк","first_name":"Мария","relation":"0"},"color":"rgb(79,106,149)","size":46.410255432128906},{"label":"Olga Koch","x":389.5440673828125,"y":1178.7476806640625,"id":"83","attributes":{"country":"1","Modularity Class":"10","photo_50":"https://pp.userapi.com/c841023/v841023250/6d627/cp-lRUvhA58.jpg","screen_name":"id401754610","city":"0","sex":"1","last_name":"Koch","first_name":"Olga"},"color":"rgb(79,106,149)","size":43.333335876464844},{"label":"Анна Волегова","x":1023.169189453125,"y":-754.3599853515625,"id":"86","attributes":{"country":"1","bdate":"10.9","Modularity Class":"17","photo_50":"https://pp.userapi.com/c841628/v841628323/53765/iFDqTuNsW5w.jpg","screen_name":"i_hitori","city":"1","sex":"1","last_name":"Волегова","first_name":"Анна","relation":"7"},"color":"rgb(0,191,246)","size":31.0256404876709},{"label":"Настя Берендеева","x":19.519710540771484,"y":39.705806732177734,"id":"7","attributes":{"Modularity Class":"5","photo_50":"https://vk.com/images/deactivated_50.png","sex":"1","last_name":"Берендеева","first_name":"Настя"},"color":"rgb(0,174,152)","size":31.0256404876709},{"label":"Карина Гукасян","x":337.9571533203125,"y":705.008544921875,"id":"37","attributes":{"country":"1","bdate":"20.7.1999","Modularity Class":"10","photo_50":"https://pp.userapi.com/c639717/v639717069/560d8/z6Zd3_zuXpw.jpg","screen_name":"id131525587","city":"1311","sex":"1","last_name":"Гукасян","first_name":"Карина","relation":"0"},"color":"rgb(79,106,149)","size":47.43589782714844},{"label":"Алина Марлинская","x":1233.4840087890625,"y":16.680831909179688,"id":"35","attributes":{"country":"1","bdate":"26.10","Modularity Class":"6","photo_50":"https://pp.userapi.com/c845321/v845321169/3afe6/x18dN7eqxu0.jpg","screen_name":"bermudattriangle","city":"0","sex":"1","last_name":"Марлинская","first_name":"Алина"},"color":"rgb(0,178,62)","size":30.0},{"label":"Николай Острогов","x":-723.9085083007812,"y":682.1851196289062,"id":"11","attributes":{"Modularity Class":"2","photo_50":"https://vk.com/images/deactivated_50.png","sex":"2","last_name":"Острогов","first_name":"Николай"},"color":"rgb(255,82,0)","size":32.56410217285156},{"label":"Вика Фёдорова","x":79.89643859863281,"y":-717.1317749023438,"id":"0","attributes":{"country":"1","bdate":"18.4","Modularity Class":"8","photo_50":"https://pp.userapi.com/c824600/v824600081/7c492/6ldUa67LIQ4.jpg","screen_name":"victorywest","city":"2","sex":"1","last_name":"Фёдорова","first_name":"Вика","relation":"0"},"color":"rgb(99,172,0)","size":41.28205108642578},{"label":"Даша Бугрова","x":679.314453125,"y":750.5687255859375,"id":"27","attributes":{"country":"0","bdate":"11.3","Modularity Class":"10","photo_50":"https://pp.userapi.com/c844724/v844724779/3d464/ODfOdrhotO4.jpg","screen_name":"id99833409","city":"0","sex":"1","last_name":"Бугрова","first_name":"Даша","relation":"0"},"color":"rgb(79,106,149)","size":46.410255432128906},{"label":"Алёна Степанова","x":-989.2537841796875,"y":-773.2616577148438,"id":"29","attributes":{"country":"1","bdate":"26.3","Modularity Class":"13","photo_50":"https://sun1-19.userapi.com/c840423/v840423252/74f0c/ttl8ZceRDNY.jpg","screen_name":"id105345113","city":"0","sex":"1","last_name":"Степанова","first_name":"Алёна","relation":"0"},"color":"rgb(39,130,69)","size":31.0256404876709},{"label":"Даша Харабрина","x":-531.5928344726562,"y":873.9447021484375,"id":"8","attributes":{"country":"19","bdate":"16.3","Modularity Class":"5","photo_50":"https://pp.userapi.com/c831308/v831308167/5799b/IQkGieVjN_8.jpg","screen_name":"kharabric","city":"0","sex":"1","last_name":"Харабрина","first_name":"Даша"},"color":"rgb(0,174,152)","size":33.589744567871094},{"label":"Lonely Whale","x":-76.0009994506836,"y":311.685791015625,"id":"85","attributes":{"country":"97","Modularity Class":"5","photo_50":"https://pp.userapi.com/c844724/v844724927/1d85d/s-9SQf6lZzU.jpg","screen_name":"boobyunee92","city":"21941","sex":"2","last_name":"Whale","first_name":"Lonely","relation":"3"},"color":"rgb(0,174,152)","size":33.589744567871094},{"label":"Настя Берендеева","x":112.00575256347656,"y":543.5225830078125,"id":"87","attributes":{"country":"1","bdate":"3.9","Modularity Class":"10","photo_50":"https://pp.userapi.com/c841026/v841026539/6ab88/0cyqIHBYnWk.jpg","screen_name":"id443342627","city":"1","sex":"1","last_name":"Берендеева","first_name":"Настя","relation":"0"},"color":"rgb(79,106,149)","size":50.0},{"label":"Шерали Машанло","x":581.1070556640625,"y":-1119.786865234375,"id":"58","attributes":{"country":"18","bdate":"29.12","Modularity Class":"16","photo_50":"https://pp.userapi.com/c845019/v845019975/3cc30/PZ1rtpegxu8.jpg","screen_name":"id198345591","city":"194","sex":"2","last_name":"Машанло","first_name":"Шерали","relation":"7"},"color":"rgb(173,73,93)","size":31.0256404876709},{"label":"Харитон Гончаров","x":-822.48974609375,"y":-971.9358520507812,"id":"72","attributes":{"country":"88","Modularity Class":"13","photo_50":"https://sun1-3.userapi.com/c840622/v840622710/718c8/OqgQUXVr1iQ.jpg","screen_name":"id266286781","city":"1932468","sex":"2","last_name":"Гончаров","first_name":"Харитон","relation":"2"},"color":"rgb(39,130,69)","size":31.538461685180664},{"label":"Саша Захарова","x":-1182.9329833984375,"y":463.11370849609375,"id":"44","attributes":{"country":"1","bdate":"5.10","Modularity Class":"2","photo_50":"https://pp.userapi.com/c412925/v412925361/26dc/gAYljX2JaMA.jpg","screen_name":"id140030361","city":"1","sex":"1","last_name":"Захарова","first_name":"Саша","relation":"6"},"color":"rgb(255,82,0)","size":31.0256404876709},{"label":"Анастасия Бояркина","x":904.6903686523438,"y":-23.977731704711914,"id":"48","attributes":{"country":"1","bdate":"19.3.1999","Modularity Class":"0","photo_50":"https://pp.userapi.com/c840137/v840137632/7cabc/693DFo1wkSo.jpg","screen_name":"anastasialykke","city":"1","sex":"1","last_name":"Бояркина","first_name":"Анастасия","relation":"0"},"color":"rgb(199,131,0)","size":34.10256576538086},{"label":"Стефа Личутина","x":-410.29083251953125,"y":-857.7177124023438,"id":"39","attributes":{"country":"0","bdate":"5.8","Modularity Class":"8","photo_50":"https://pp.userapi.com/c841339/v841339901/974a/JQYWCX5Uyas.jpg","screen_name":"likephantom","city":"0","sex":"1","last_name":"Личутина","first_name":"Стефа"},"color":"rgb(99,172,0)","size":41.28205108642578},{"label":"Кристина Балашова","x":327.2620849609375,"y":-1195.6312255859375,"id":"23","attributes":{"country":"1","bdate":"15.4","Modularity Class":"8","photo_50":"https://pp.userapi.com/c824204/v824204368/7c629/M7DtoWCwkvk.jpg","screen_name":"neverberries","city":"95","sex":"1","last_name":"Балашова","first_name":"Кристина","relation":"0"},"color":"rgb(99,172,0)","size":39.230770111083984},{"label":"Анатолий Донцов","x":857.94384765625,"y":498.89324951171875,"id":"49","attributes":{"country":"1","bdate":"15.5.1999","Modularity Class":"10","photo_50":"https://sun1-19.userapi.com/c840726/v840726162/5829e/ga6NBK3izj4.jpg","screen_name":"dontsov1999","city":"0","sex":"2","last_name":"Донцов","first_name":"Анатолий","relation":"0"},"color":"rgb(79,106,149)","size":45.38461685180664},{"label":"Екатерина Андреевна","x":-170.45350646972656,"y":-1267.2603759765625,"id":"54","attributes":{"country":"0","bdate":"21.2.1998","Modularity Class":"8","photo_50":"https://pp.userapi.com/c841524/v841524483/6ed6a/8CNK-G_GrsQ.jpg","screen_name":"id185235856","city":"0","sex":"1","last_name":"Андреевна","first_name":"Екатерина","relation":"0"},"color":"rgb(99,172,0)","size":40.25640869140625},{"label":"Никита Коновалов","x":-342.18829345703125,"y":355.42034912109375,"id":"67","attributes":{"country":"1","bdate":"15.4","Modularity Class":"5","photo_50":"https://pp.userapi.com/c830508/v830508630/d38e7/ecWfqJ8BQ1A.jpg","screen_name":"ikonovalovvk","city":"1","sex":"2","last_name":"Коновалов","first_name":"Никита","relation":"7"},"color":"rgb(0,174,152)","size":33.589744567871094},{"label":"Миша Ким","x":-1265.275390625,"y":-74.04196166992188,"id":"56","attributes":{"country":"1","bdate":"14.2","Modularity Class":"2","photo_50":"https://pp.userapi.com/c845019/v845019569/38352/os6zOhpP1wU.jpg","screen_name":"mikhail.baglay","city":"1","sex":"2","last_name":"Ким","first_name":"Миша"},"color":"rgb(255,82,0)","size":32.0512809753418},{"label":"Иванна Бирюкова","x":30.247821807861328,"y":-964.1143798828125,"id":"19","attributes":{"country":"1","bdate":"11.10","Modularity Class":"8","photo_50":"https://pp.userapi.com/c846017/v846017180/16511/3nUzNqOYovY.jpg","screen_name":"biryukas","city":"1","sex":"1","last_name":"Бирюкова","first_name":"Иванна","relation":"0"},"color":"rgb(99,172,0)","size":41.28205108642578},{"label":"Илья Леонтьев","x":-849.9195556640625,"y":-510.3309326171875,"id":"40","attributes":{"country":"0","Modularity Class":"2","photo_50":"https://pp.userapi.com/c824204/v824204583/9d3aa/vATyI9wNr0c.jpg","screen_name":"welaillusion","city":"0","sex":"2","last_name":"Леонтьев","first_name":"Илья"},"color":"rgb(255,82,0)","size":31.0256404876709},{"label":"Екатерина Стоянова","x":-622.8653564453125,"y":396.99578857421875,"id":"75","attributes":{"country":"0","bdate":"30.8","Modularity Class":"2","photo_50":"https://pp.userapi.com/c845121/v845121339/29484/Wn2ouV4svus.jpg","screen_name":"ms.coccinelle","city":"0","sex":"1","last_name":"Стоянова","first_name":"Екатерина","relation":"0"},"color":"rgb(255,82,0)","size":35.64102554321289},{"label":"Екатерина Борисова","x":-181.30816650390625,"y":593.2730102539062,"id":"22","attributes":{"country":"1","bdate":"18.1","Modularity Class":"5","photo_50":"https://pp.userapi.com/c633122/v633122641/2d8b5/1U-8x9DomZc.jpg","screen_name":"id87743641","city":"1","sex":"1","last_name":"Борисова","first_name":"Екатерина","relation":"0"},"color":"rgb(0,174,152)","size":37.17948913574219},{"label":"Аркаша Персик","x":-1127.58203125,"y":-558.0468139648438,"id":"66","attributes":{"Modularity Class":"13","photo_50":"https://vk.com/images/deactivated_50.png","sex":"2","last_name":"Персик","first_name":"Аркаша"},"color":"rgb(39,130,69)","size":30.512821197509766},{"label":"Дмитрий Подгорный","x":-254.20477294921875,"y":76.52114868164062,"id":"6","attributes":{"country":"1","bdate":"17.8.1998","Modularity Class":"10","photo_50":"https://pp.userapi.com/c824409/v824409851/36327/Ldcqgl4nhO8.jpg","screen_name":"indrauv","city":"1","sex":"2","last_name":"Подгорный","first_name":"Дмитрий","relation":"0"},"color":"rgb(79,106,149)","size":30.512821197509766},{"label":"Стася Захарова","x":-1051.8529052734375,"y":706.4652099609375,"id":"36","attributes":{"country":"1","bdate":"5.10","Modularity Class":"2","photo_50":"https://pp.userapi.com/c11508/u127060568/e_3351a079.jpg","screen_name":"id127060568","city":"1","sex":"1","last_name":"Захарова","first_name":"Стася","relation":"6"},"color":"rgb(255,82,0)","size":31.0256404876709},{"label":"Настя Кулиш","x":-982.39404296875,"y":256.6904296875,"id":"42","attributes":{"country":"1","bdate":"6.4.1999","Modularity Class":"2","photo_50":"https://pp.userapi.com/c417725/v417725273/53f7/TDinlyyVFMU.jpg","screen_name":"id137428273","city":"1","sex":"1","last_name":"Кулиш","first_name":"Настя","relation":"0"},"color":"rgb(255,82,0)","size":38.71794891357422},{"label":"Таня Парфёнова","x":564.30419921875,"y":-501.1158752441406,"id":"57","attributes":{"country":"1","Modularity Class":"11","photo_50":"https://pp.userapi.com/c841532/v841532278/51635/iQzo_XL4dSU.jpg","screen_name":"psoast","city":"1","sex":"1","last_name":"Парфёнова","first_name":"Таня","relation":"0"},"color":"rgb(255,57,173)","size":32.0512809753418},{"label":"Маша Рихтер","x":558.778076171875,"y":-853.7467041015625,"id":"65","attributes":{"country":"0","bdate":"28.2","Modularity Class":"11","photo_50":"https://pp.userapi.com/c840024/v840024834/8867e/jIu_Dyk5ICk.jpg","screen_name":"uf0p4rty","city":"0","sex":"1","last_name":"Рихтер","first_name":"Маша"},"color":"rgb(255,57,173)","size":33.07692337036133},{"label":"Алина Курашова","x":-505.5514831542969,"y":116.27647399902344,"id":"2","attributes":{"country":"1","bdate":"23.8.1988","Modularity Class":"2","photo_50":"https://pp.userapi.com/c639728/v639728680/12726/UGAB6sT2OUw.jpg","screen_name":"kurashovaaalina","city":"1","sex":"1","last_name":"Курашова","first_name":"Алина","relation":"0"},"color":"rgb(255,82,0)","size":37.17948913574219},{"label":"Софья Ляхова","x":-264.4195861816406,"y":865.1876831054688,"id":"14","attributes":{"country":"0","bdate":"8.1","Modularity Class":"5","photo_50":"https://pp.userapi.com/c639820/v639820938/4eaef/W2pmAMScDL0.jpg","screen_name":"slyakhovapll","city":"0","sex":"1","last_name":"Ляхова","first_name":"Софья","relation":"0"},"color":"rgb(0,174,152)","size":35.128204345703125},{"label":"Мария Шмелёва","x":-206.386962890625,"y":1267.7056884765625,"id":"34","attributes":{"country":"1","bdate":"19.1","Modularity Class":"5","photo_50":"https://pp.userapi.com/c841221/v841221001/e839/ajH3lkK0kUM.jpg","screen_name":"id118472500","city":"1","sex":"1","last_name":"Шмелёва","first_name":"Мария","relation":"0"},"color":"rgb(0,174,152)","size":33.589744567871094},{"label":"Екатерина Смирнова","x":210.9526824951172,"y":969.1236572265625,"id":"62","attributes":{"country":"1","bdate":"14.8","Modularity Class":"10","photo_50":"https://pp.userapi.com/c638017/v638017116/60100/P3u9N2oEatA.jpg","screen_name":"smth_difficult","city":"1","sex":"1","last_name":"Смирнова","first_name":"Екатерина","relation":"0"},"color":"rgb(79,106,149)","size":46.410255432128906},{"label":"Саша Гризли","x":-443.653564453125,"y":-143.64205932617188,"id":"59","attributes":{"country":"1","bdate":"5.10","Modularity Class":"2","photo_50":"https://pp.userapi.com/c621629/v621629821/c00b/KiZuCU96Yi8.jpg","screen_name":"sashagriz","city":"1","sex":"1","last_name":"Гризли","first_name":"Саша","relation":"0"},"color":"rgb(255,82,0)","size":34.10256576538086},{"label":"Римма Мальцева","x":976.9178466796875,"y":740.1510620117188,"id":"30","attributes":{"country":"1","bdate":"5.11","Modularity Class":"10","photo_50":"https://pp.userapi.com/c830309/v830309940/372aa/8MFFyRRSjGw.jpg","screen_name":"rimma2013","city":"1","sex":"1","last_name":"Мальцева","first_name":"Римма","relation":"0"},"color":"rgb(79,106,149)","size":45.38461685180664},{"label":"Вика Апполонова","x":459.8854675292969,"y":905.1171264648438,"id":"46","attributes":{"country":"1","bdate":"20.2","Modularity Class":"10","photo_50":"https://pp.userapi.com/c831508/v831508148/cb8b0/TGYV8jukbyY.jpg","screen_name":"id143739831","city":"1","sex":"1","last_name":"Апполонова","first_name":"Вика","relation":"0"},"color":"rgb(79,106,149)","size":46.410255432128906},{"label":"Елизавета Белицер","x":-713.41455078125,"y":-120.63093566894531,"id":"43","attributes":{"country":"1","bdate":"9.5","Modularity Class":"2","photo_50":"https://pp.userapi.com/c636029/v636029179/2dfa7/v_uDuBWPpV0.jpg","screen_name":"id139268179","city":"1","sex":"1","last_name":"Белицер","first_name":"Елизавета"},"color":"rgb(255,82,0)","size":38.20512771606445},{"label":"Great Good","x":-1002.6473999023438,"y":-16.91082763671875,"id":"70","attributes":{"country":"0","Modularity Class":"2","photo_50":"https://pp.userapi.com/c624518/v624518173/49610/YQYf7n8ak1M.jpg","screen_name":"wheeze252","city":"0","sex":"1","last_name":"Good","first_name":"Great","relation":"0"},"color":"rgb(255,82,0)","size":35.128204345703125},{"label":"Екатерина Красильникова","x":125.09284210205078,"y":1232.082763671875,"id":"10","attributes":{"country":"1","bdate":"29.8","Modularity Class":"10","photo_50":"https://pp.userapi.com/c836234/v836234960/35624/A-2YmFnSLhc.jpg","screen_name":"katyashka_kras","city":"1","sex":"1","last_name":"Красильникова","first_name":"Екатерина","relation":"0"},"color":"rgb(79,106,149)","size":39.230770111083984},{"label":"Анастасия Коротина","x":208.60525512695312,"y":240.56553649902344,"id":"38","attributes":{"country":"1","bdate":"15.3","Modularity Class":"10","photo_50":"https://pp.userapi.com/c638921/v638921204/4a3a8/g4dD7xoGnQw.jpg","screen_name":"thebreathofdeath","city":"1","sex":"1","last_name":"Коротина","first_name":"Анастасия","relation":"4"},"color":"rgb(79,106,149)","size":42.30769348144531},{"label":"Влада Образцова","x":-185.42828369140625,"y":-681.9415893554688,"id":"50","attributes":{"country":"3","bdate":"5.2","Modularity Class":"8","photo_50":"https://pp.userapi.com/c824504/v824504717/22818/N-rfMNtNBUI.jpg","screen_name":"vluxette","city":"0","sex":"1","last_name":"Образцова","first_name":"Влада","relation":"2"},"color":"rgb(99,172,0)","size":42.30769348144531},{"label":"Саша Мордор","x":-136.8759307861328,"y":-190.9246826171875,"id":"74","attributes":{"country":"1","bdate":"18.9","Modularity Class":"11","photo_50":"https://pp.userapi.com/c630623/v630623819/43694/baCpdlR0S9k.jpg","screen_name":"crnrhns","city":"2","sex":"1","last_name":"Мордор","first_name":"Саша","relation":"0"},"color":"rgb(255,57,173)","size":31.0256404876709},{"label":"Vincent Rosenberg","x":-586.1043090820312,"y":-1049.676025390625,"id":"68","attributes":{"country":"226","bdate":"30.7.1995","Modularity Class":"8","photo_50":"https://sun1-17.userapi.com/c840530/v840530527/7e2a8/cI_lDC9MsWg.jpg","screen_name":"godblessminyoongi","city":"1713816","sex":"2","last_name":"Rosenberg","first_name":"Vincent","relation":"2"},"color":"rgb(99,172,0)","size":39.230770111083984},{"label":"Мария Никитина","x":84.1745376586914,"y":-1230.7100830078125,"id":"16","attributes":{"country":"1","bdate":"22.7","Modularity Class":"8","photo_50":"https://sun1-3.userapi.com/c840721/v840721697/7260a/eiC5zF-DZv4.jpg","screen_name":"mary_nope","city":"60","sex":"1","last_name":"Никитина","first_name":"Мария","relation":"0"},"color":"rgb(99,172,0)","size":40.25640869140625},{"label":"DELETED ","x":320.7865295410156,"y":-11.078753471374512,"id":"24","attributes":{"Modularity Class":"5","photo_50":"https://vk.com/images/deactivated_50.png","sex":"1","first_name":"DELETED"},"color":"rgb(0,174,152)","size":30.512821197509766},{"label":"Саша Гладышевская","x":-86.9555892944336,"y":1049.0322265625,"id":"28","attributes":{"country":"1","bdate":"27.9","Modularity Class":"10","photo_50":"https://pp.userapi.com/c836138/v836138970/a1b2/alxDb0mGn8Q.jpg","screen_name":"alexandraglad","city":"1","sex":"1","last_name":"Гладышевская","first_name":"Саша"},"color":"rgb(79,106,149)","size":31.0256404876709},{"label":"Саша Мор","x":-21.587617874145508,"y":-446.289306640625,"id":"81","attributes":{"country":"1","bdate":"18.9","Modularity Class":"11","photo_50":"https://pp.userapi.com/c830309/v830309386/d895d/Ap-pINKxG2Q.jpg","screen_name":"mor.s666","city":"1","sex":"2","last_name":"Мор","first_name":"Саша","relation":"0"},"color":"rgb(255,57,173)","size":31.0256404876709},{"label":"Жанетта Атанская","x":612.4674682617188,"y":8.876599311828613,"id":"32","attributes":{"country":"1","bdate":"13.4","Modularity Class":"0","photo_50":"https://pp.userapi.com/c840026/v840026773/2669b/2xb_uMWKkIY.jpg","screen_name":"ajanette777","city":"1","sex":"1","nickname":"Ƹ̵̡Ӝ̵̨̄Ʒ AJanette Ƹ̵̡Ӝ̵̨̄Ʒ","last_name":"Атанская","first_name":"Жанетта","relation":"0"},"color":"rgb(199,131,0)","size":32.0512809753418},{"label":"Валерия Ленская","x":-394.5393371582031,"y":-1189.6590576171875,"id":"47","attributes":{"country":"1","bdate":"2.3","Modularity Class":"8","photo_50":"https://pp.userapi.com/c841324/v841324019/7b8a0/QP3inv4HrzI.jpg","screen_name":"id_mcr","city":"2","sex":"1","last_name":"Ленская","first_name":"Валерия","relation":"7"},"color":"rgb(99,172,0)","size":40.25640869140625},{"label":"Юлия Майстренко","x":762.160400390625,"y":-693.2064208984375,"id":"61","attributes":{"country":"1","Modularity Class":"9","photo_50":"https://pp.userapi.com/c837627/v837627077/5023c/nqEH1fWRiJ4.jpg","screen_name":"id212035077","city":"49","sex":"1","last_name":"Майстренко","first_name":"Юлия","relation":"0"},"color":"rgb(0,133,142)","size":30.0},{"label":"Анна Шарко","x":-450.27313232421875,"y":-606.54638671875,"id":"45","attributes":{"country":"3","bdate":"21.4","Modularity Class":"8","photo_50":"https://sun1-1.userapi.com/c840531/v840531963/69e52/9CSidwXdL9s.jpg","screen_name":"hannasharko","city":"282","sex":"1","last_name":"Шарко","first_name":"Анна","relation":"0"},"color":"rgb(99,172,0)","size":37.17948913574219},{"label":"Анна Голикова","x":1267.80859375,"y":-254.06509399414062,"id":"4","attributes":{"country":"1","bdate":"29.4","Modularity Class":"1","photo_50":"https://pp.userapi.com/c824601/v824601347/79778/Q6MZxtLl0k0.jpg","screen_name":"golikovaann","city":"35","sex":"1","last_name":"Голикова","first_name":"Анна","relation":"2"},"color":"rgb(232,103,255)","size":30.0},{"label":"Артем Пак","x":264.4058837890625,"y":-460.724365234375,"id":"82","attributes":{"country":"0","Modularity Class":"16","photo_50":"https://vk.com/images/camera_50.png","screen_name":"id397844328","city":"0","sex":"2","last_name":"Пак","first_name":"Артем","relation":"0"},"color":"rgb(173,73,93)","size":31.0256404876709},{"label":"Анна Дарбинян","x":361.15899658203125,"y":-690.4719848632812,"id":"31","attributes":{"country":"1","bdate":"17.3","Modularity Class":"8","photo_50":"https://sun1-18.userapi.com/c840731/v840731587/75af9/E3g7xBXcCmY.jpg","screen_name":"darbinyashka1999","city":"144","sex":"1","last_name":"Дарбинян","first_name":"Анна","relation":"5"},"color":"rgb(99,172,0)","size":34.10256576538086},{"label":"Инга Каспаравичуте","x":1149.66259765625,"y":534.6717529296875,"id":"52","attributes":{"country":"1","bdate":"7.4","Modularity Class":"10","photo_50":"https://pp.userapi.com/c824502/v824502186/fe170/Sbsuw2Killg.jpg","screen_name":"id180386057","city":"61","sex":"1","last_name":"Каспаравичуте","first_name":"Инга","relation":"0"},"color":"rgb(79,106,149)","size":39.230770111083984},{"label":"Юлия Ли","x":835.5385131835938,"y":939.6716918945312,"id":"60","attributes":{"country":"1","bdate":"2.12","Modularity Class":"10","photo_50":"https://pp.userapi.com/c840227/v840227974/837f2/5dPZqNx4Ckw.jpg","screen_name":"juliadderly","city":"0","sex":"1","last_name":"Ли","first_name":"Юлия","relation":"0"},"color":"rgb(79,106,149)","size":45.38461685180664},{"label":"Валерия Хонявина","x":-678.6659545898438,"y":1094.79248046875,"id":"17","attributes":{"country":"0","Modularity Class":"5","photo_50":"https://vk.com/images/camera_50.png","screen_name":"valerigoi","city":"0","sex":"1","last_name":"Хонявина","first_name":"Валерия","relation":"0"},"color":"rgb(0,174,152)","size":30.512821197509766},{"label":"Дарья Котыкова","x":1000.7813720703125,"y":-227.77529907226562,"id":"20","attributes":{"country":"1","bdate":"14.12.1997","Modularity Class":"4","photo_50":"https://sun1-2.userapi.com/c840722/v840722108/78d93/l1Ex9xYlwMQ.jpg","screen_name":"darya_kotykova","city":"95","sex":"1","nickname":"† 欠けている †","last_name":"Котыкова","first_name":"Дарья","relation":"2"},"color":"rgb(0,161,245)","size":30.0},{"label":"Дима Сон","x":140.06228637695312,"y":-213.1504669189453,"id":"53","attributes":{"country":"226","bdate":"6.7.1995","Modularity Class":"7","photo_50":"https://pp.userapi.com/c628020/v628020307/4dcaf/0DsnxnnvYeE.jpg","screen_name":"id182418307","city":"1903398","sex":"2","last_name":"Сон","first_name":"Дима","relation":"0"},"color":"rgb(255,50,96)","size":30.0},{"label":"정미 이","x":706.9898681640625,"y":-247.90966796875,"id":"84","attributes":{"country":"0","bdate":"25.1","Modularity Class":"5","photo_50":"https://pp.userapi.com/c846019/v846019677/35185/RIhtbT7XpjM.jpg","screen_name":"jmlee","city":"0","sex":"1","last_name":"이","first_name":"정미","relation":"0"},"color":"rgb(0,174,152)","size":31.0256404876709},{"label":"Юлия Сыса","x":725.5009155273438,"y":319.4437561035156,"id":"9","attributes":{"country":"0","bdate":"25.8","Modularity Class":"10","photo_50":"https://pp.userapi.com/c844216/v844216420/1ac24/9pcowb0NwNI.jpg","screen_name":"id54636232","city":"0","sex":"1","last_name":"Сыса","first_name":"Юлия","relation":"6"},"color":"rgb(79,106,149)","size":47.43589782714844}],"edges":[{"source":"13","target":"18","id":"73","attributes":{},"color":"rgb(99,172,0)","size":1.0},{"source":"69","target":"60","id":"454","attributes":{},"color":"rgb(79,106,149)","size":1.0},{"source":"75","target":"1","id":"487","attributes":{},"color":"rgb(255,82,0)","size":1.0},{"source":"51","target":"64","id":"339","attributes":{},"color":"rgb(79,106,149)","size":1.0},{"source":"22","target":"7","id":"131","attributes":{},"color":"rgb(0,174,152)","size":1.0},{"source":"42","target":"36","id":"251","attributes":{},"color":"rgb(255,82,0)","size":1.0},{"source":"49","target":"64","id":"312","attributes":{},"color":"rgb(79,106,149)","size":1.0},{"source":"27","target":"37","id":"161","attributes":{},"color":"rgb(79,106,149)","size":1.0},{"source":"37","target":"27","id":"208","attributes":{},"color":"rgb(79,106,149)","size":1.0},{"source":"34","target":"21","id":"201","attributes":{},"color":"rgb(0,174,152)","size":1.0},{"source":"37","target":"83","id":"220","attributes":{},"color":"rgb(79,106,149)","size":1.0},{"source":"63","target":"70","id":"410","attributes":{},"color":"rgb(255,82,0)","size":1.0},{"source":"73","target":"38","id":"474","attributes":{},"color":"rgb(79,106,149)","size":1.0},{"source":"73","target":"80","id":"483","attributes":{},"color":"rgb(79,106,149)","size":1.0},{"source":"2","target":"15","id":"17","attributes":{},"color":"rgb(255,82,0)","size":1.0},{"source":"38","target":"73","id":"231","attributes":{},"color":"rgb(79,106,149)","size":1.0},{"source":"39","target":"16","id":"236","attributes":{},"color":"rgb(99,172,0)","size":1.0},{"source":"14","target":"8","id":"80","attributes":{},"color":"rgb(0,174,152)","size":1.0},{"source":"14","target":"26","id":"82","attributes":{},"color":"rgb(0,174,152)","size":1.0},{"source":"78","target":"25","id":"493","attributes":{},"color":"rgb(255,82,0)","size":1.0},{"source":"21","target":"22","id":"126","attributes":{},"color":"rgb(0,174,152)","size":1.0},{"source":"5","target":"15","id":"34","attributes":{},"color":"rgb(255,82,0)","size":1.0},{"source":"10","target":"87","id":"70","attributes":{},"color":"rgb(79,106,149)","size":1.0},{"source":"26","target":"22","id":"157","attributes":{},"color":"rgb(0,174,152)","size":1.0},{"source":"63","target":"2","id":"405","attributes":{},"color":"rgb(255,82,0)","size":1.0},{"source":"51","target":"62","id":"338","attributes":{},"color":"rgb(79,106,149)","size":1.0},{"source":"49","target":"27","id":"304","attributes":{},"color":"rgb(79,106,149)","size":1.0},{"source":"62","target":"10","id":"390","attributes":{},"color":"rgb(79,106,149)","size":1.0},{"source":"64","target":"46","id":"418","attributes":{},"color":"rgb(79,106,149)","size":1.0},{"source":"59","target":"43","id":"373","attributes":{},"color":"rgb(255,82,0)","size":1.0},{"source":"64","target":"60","id":"422","attributes":{},"color":"rgb(79,106,149)","size":1.0},{"source":"56","target":"78","id":"366","attributes":{},"color":"rgb(255,82,0)","size":1.0},{"source":"75","target":"11","id":"490","attributes":{},"color":"rgb(255,82,0)","size":1.0},{"source":"51","target":"10","id":"330","attributes":{},"color":"rgb(79,106,149)","size":1.0},{"source":"73","target":"51","id":"478","attributes":{},"color":"rgb(79,106,149)","size":1.0},{"source":"69","target":"80","id":"458","attributes":{},"color":"rgb(79,106,149)","size":1.0},{"source":"0","target":"13","id":"1","attributes":{},"color":"rgb(99,172,0)","size":1.0},{"source":"46","target":"30","id":"275","attributes":{},"color":"rgb(79,106,149)","size":1.0},{"source":"73","target":"87","id":"485","attributes":{},"color":"rgb(79,106,149)","size":1.0},{"source":"38","target":"9","id":"223","attributes":{},"color":"rgb(79,106,149)","size":1.0},{"source":"67","target":"7","id":"431","attributes":{},"color":"rgb(0,174,152)","size":1.0},{"source":"26","target":"21","id":"156","attributes":{},"color":"rgb(0,174,152)","size":1.0},{"source":"54","target":"19","id":"358","attributes":{},"color":"rgb(99,172,0)","size":1.0},{"source":"83","target":"51","id":"518","attributes":{},"color":"rgb(79,106,149)","size":1.0},{"source":"51","target":"83","id":"343","attributes":{},"color":"rgb(79,106,149)","size":1.0},{"source":"9","target":"37","id":"48","attributes":{},"color":"rgb(79,106,149)","size":1.0},{"source":"46","target":"83","id":"286","attributes":{},"color":"rgb(79,106,149)","size":1.0},{"source":"51","target":"60","id":"337","attributes":{},"color":"rgb(79,106,149)","size":1.0},{"source":"87","target":"51","id":"539","attributes":{},"color":"rgb(79,106,149)","size":1.0},{"source":"62","target":"87","id":"404","attributes":{},"color":"rgb(79,106,149)","size":1.0},{"source":"62","target":"51","id":"397","attributes":{},"color":"rgb(79,106,149)","size":1.0},{"source":"39","target":"18","id":"237","attributes":{},"color":"rgb(99,172,0)","size":1.0},{"source":"0","target":"47","id":"8","attributes":{},"color":"rgb(99,172,0)","size":1.0},{"source":"15","target":"11","id":"87","attributes":{},"color":"rgb(255,82,0)","size":1.0},{"source":"50","target":"0","id":"317","attributes":{},"color":"rgb(99,172,0)","size":1.0},{"source":"87","target":"37","id":"535","attributes":{},"color":"rgb(79,106,149)","size":1.0},{"source":"31","target":"65","id":"195","attributes":{},"color":"rgb(177,114,86)","size":1.0},{"source":"49","target":"83","id":"315","attributes":{},"color":"rgb(79,106,149)","size":1.0},{"source":"18","target":"45","id":"109","attributes":{},"color":"rgb(99,172,0)","size":1.0},{"source":"30","target":"62","id":"186","attributes":{},"color":"rgb(79,106,149)","size":1.0},{"source":"56","target":"25","id":"365","attributes":{},"color":"rgb(255,82,0)","size":1.0},{"source":"64","target":"38","id":"417","attributes":{},"color":"rgb(79,106,149)","size":1.0},{"source":"10","target":"37","id":"62","attributes":{},"color":"rgb(79,106,149)","size":1.0},{"source":"39","target":"47","id":"241","attributes":{},"color":"rgb(99,172,0)","size":1.0},{"source":"64","target":"9","id":"412","attributes":{},"color":"rgb(79,106,149)","size":1.0},{"source":"18","target":"39","id":"108","attributes":{},"color":"rgb(99,172,0)","size":1.0},{"source":"22","target":"67","id":"137","attributes":{},"color":"rgb(0,174,152)","size":1.0},{"source":"39","target":"68","id":"244","attributes":{},"color":"rgb(99,172,0)","size":1.0},{"source":"46","target":"64","id":"282","attributes":{},"color":"rgb(79,106,149)","size":1.0},{"source":"51","target":"87","id":"344","attributes":{},"color":"rgb(79,106,149)","size":1.0},{"source":"37","target":"3","id":"205","attributes":{},"color":"rgb(79,106,149)","size":1.0},{"source":"13","target":"39","id":"76","attributes":{},"color":"rgb(99,172,0)","size":1.0},{"source":"62","target":"60","id":"398","attributes":{},"color":"rgb(79,106,149)","size":1.0},{"source":"87","target":"64","id":"542","attributes":{},"color":"rgb(79,106,149)","size":1.0},{"source":"9","target":"80","id":"59","attributes":{},"color":"rgb(79,106,149)","size":1.0},{"source":"27","target":"62","id":"168","attributes":{},"color":"rgb(79,106,149)","size":1.0},{"source":"31","target":"50","id":"194","attributes":{},"color":"rgb(99,172,0)","size":1.0},{"source":"39","target":"23","id":"239","attributes":{},"color":"rgb(99,172,0)","size":1.0},{"source":"59","target":"15","id":"371","attributes":{},"color":"rgb(255,82,0)","size":1.0},{"source":"13","target":"54","id":"79","attributes":{},"color":"rgb(99,172,0)","size":1.0},{"source":"64","target":"27","id":"414","attributes":{},"color":"rgb(79,106,149)","size":1.0},{"source":"83","target":"10","id":"512","attributes":{},"color":"rgb(79,106,149)","size":1.0},{"source":"8","target":"14","id":"41","attributes":{},"color":"rgb(0,174,152)","size":1.0},{"source":"19","target":"31","id":"119","attributes":{},"color":"rgb(99,172,0)","size":1.0},{"source":"21","target":"34","id":"128","attributes":{},"color":"rgb(0,174,152)","size":1.0},{"source":"19","target":"16","id":"116","attributes":{},"color":"rgb(99,172,0)","size":1.0},{"source":"47","target":"13","id":"289","attributes":{},"color":"rgb(99,172,0)","size":1.0},{"source":"87","target":"46","id":"537","attributes":{},"color":"rgb(79,106,149)","size":1.0},{"source":"39","target":"50","id":"242","attributes":{},"color":"rgb(99,172,0)","size":1.0},{"source":"3","target":"38","id":"26","attributes":{},"color":"rgb(79,106,149)","size":1.0},{"source":"5","target":"26","id":"36","attributes":{},"color":"rgb(127,128,76)","size":1.0},{"source":"0","target":"50","id":"9","attributes":{},"color":"rgb(99,172,0)","size":1.0},{"source":"16","target":"18","id":"96","attributes":{},"color":"rgb(99,172,0)","size":1.0},{"source":"32","target":"73","id":"197","attributes":{},"color":"rgb(139,118,74)","size":1.0},{"source":"50","target":"23","id":"322","attributes":{},"color":"rgb(99,172,0)","size":1.0},{"source":"64","target":"49","id":"419","attributes":{},"color":"rgb(79,106,149)","size":1.0},{"source":"74","target":"57","id":"486","attributes":{},"color":"rgb(255,57,173)","size":1.0},{"source":"0","target":"16","id":"2","attributes":{},"color":"rgb(99,172,0)","size":1.0},{"source":"30","target":"64","id":"187","attributes":{},"color":"rgb(79,106,149)","size":1.0},{"source":"10","target":"51","id":"64","attributes":{},"color":"rgb(79,106,149)","size":1.0},{"source":"87","target":"83","id":"546","attributes":{},"color":"rgb(79,106,149)","size":1.0},{"source":"48","target":"32","id":"299","attributes":{},"color":"rgb(199,131,0)","size":1.0},{"source":"52","target":"69","id":"352","attributes":{},"color":"rgb(79,106,149)","size":1.0},{"source":"9","target":"3","id":"45","attributes":{},"color":"rgb(79,106,149)","size":1.0},{"source":"8","target":"87","id":"44","attributes":{},"color":"rgb(39,140,150)","size":1.0},{"source":"26","target":"17","id":"155","attributes":{},"color":"rgb(0,174,152)","size":1.0},{"source":"37","target":"9","id":"206","attributes":{},"color":"rgb(79,106,149)","size":1.0},{"source":"49","target":"46","id":"307","attributes":{},"color":"rgb(79,106,149)","size":1.0},{"source":"27","target":"83","id":"173","attributes":{},"color":"rgb(79,106,149)","size":1.0},{"source":"46","target":"49","id":"278","attributes":{},"color":"rgb(79,106,149)","size":1.0},{"source":"73","target":"27","id":"470","attributes":{},"color":"rgb(79,106,149)","size":1.0},{"source":"0","target":"31","id":"5","attributes":{},"color":"rgb(99,172,0)","size":1.0},{"source":"60","target":"62","id":"382","attributes":{},"color":"rgb(79,106,149)","size":1.0},{"source":"9","target":"69","id":"57","attributes":{},"color":"rgb(79,106,149)","size":1.0},{"source":"64","target":"30","id":"415","attributes":{},"color":"rgb(79,106,149)","size":1.0},{"source":"1","target":"11","id":"13","attributes":{},"color":"rgb(255,82,0)","size":1.0},{"source":"49","target":"52","id":"309","attributes":{},"color":"rgb(79,106,149)","size":1.0},{"source":"80","target":"62","id":"504","attributes":{},"color":"rgb(79,106,149)","size":1.0},{"source":"14","target":"21","id":"81","attributes":{},"color":"rgb(0,174,152)","size":1.0},{"source":"30","target":"60","id":"185","attributes":{},"color":"rgb(79,106,149)","size":1.0},{"source":"38","target":"87","id":"233","attributes":{},"color":"rgb(79,106,149)","size":1.0},{"source":"68","target":"0","id":"435","attributes":{},"color":"rgb(99,172,0)","size":1.0},{"source":"69","target":"62","id":"455","attributes":{},"color":"rgb(79,106,149)","size":1.0},{"source":"51","target":"46","id":"334","attributes":{},"color":"rgb(79,106,149)","size":1.0},{"source":"80","target":"46","id":"500","attributes":{},"color":"rgb(79,106,149)","size":1.0},{"source":"26","target":"87","id":"158","attributes":{},"color":"rgb(39,140,150)","size":1.0},{"source":"43","target":"15","id":"257","attributes":{},"color":"rgb(255,82,0)","size":1.0},{"source":"0","target":"19","id":"3","attributes":{},"color":"rgb(99,172,0)","size":1.0},{"source":"47","target":"0","id":"288","attributes":{},"color":"rgb(99,172,0)","size":1.0},{"source":"47","target":"50","id":"295","attributes":{},"color":"rgb(99,172,0)","size":1.0},{"source":"15","target":"75","id":"93","attributes":{},"color":"rgb(255,82,0)","size":1.0},{"source":"42","target":"2","id":"247","attributes":{},"color":"rgb(255,82,0)","size":1.0},{"source":"52","target":"60","id":"350","attributes":{},"color":"rgb(79,106,149)","size":1.0},{"source":"16","target":"50","id":"101","attributes":{},"color":"rgb(99,172,0)","size":1.0},{"source":"16","target":"39","id":"99","attributes":{},"color":"rgb(99,172,0)","size":1.0},{"source":"75","target":"2","id":"488","attributes":{},"color":"rgb(255,82,0)","size":1.0},{"source":"19","target":"50","id":"122","attributes":{},"color":"rgb(99,172,0)","size":1.0},{"source":"45","target":"50","id":"270","attributes":{},"color":"rgb(99,172,0)","size":1.0},{"source":"47","target":"39","id":"293","attributes":{},"color":"rgb(99,172,0)","size":1.0},{"source":"19","target":"18","id":"117","attributes":{},"color":"rgb(99,172,0)","size":1.0},{"source":"46","target":"87","id":"287","attributes":{},"color":"rgb(79,106,149)","size":1.0},{"source":"72","target":"66","id":"467","attributes":{},"color":"rgb(39,130,69)","size":1.0},{"source":"80","target":"52","id":"502","attributes":{},"color":"rgb(79,106,149)","size":1.0},{"source":"27","target":"52","id":"166","attributes":{},"color":"rgb(79,106,149)","size":1.0},{"source":"9","target":"52","id":"53","attributes":{},"color":"rgb(79,106,149)","size":1.0},{"source":"27","target":"87","id":"174","attributes":{},"color":"rgb(79,106,149)","size":1.0},{"source":"43","target":"63","id":"261","attributes":{},"color":"rgb(255,82,0)","size":1.0},{"source":"50","target":"13","id":"318","attributes":{},"color":"rgb(99,172,0)","size":1.0},{"source":"15","target":"42","id":"88","attributes":{},"color":"rgb(255,82,0)","size":1.0},{"source":"30","target":"38","id":"180","attributes":{},"color":"rgb(79,106,149)","size":1.0},{"source":"30","target":"69","id":"188","attributes":{},"color":"rgb(79,106,149)","size":1.0},{"source":"50","target":"19","id":"321","attributes":{},"color":"rgb(99,172,0)","size":1.0},{"source":"37","target":"64","id":"216","attributes":{},"color":"rgb(79,106,149)","size":1.0},{"source":"62","target":"9","id":"389","attributes":{},"color":"rgb(79,106,149)","size":1.0},{"source":"50","target":"68","id":"328","attributes":{},"color":"rgb(99,172,0)","size":1.0},{"source":"33","target":"48","id":"199","attributes":{},"color":"rgb(199,131,0)","size":1.0},{"source":"46","target":"73","id":"284","attributes":{},"color":"rgb(79,106,149)","size":1.0},{"source":"60","target":"73","id":"385","attributes":{},"color":"rgb(79,106,149)","size":1.0},{"source":"10","target":"62","id":"65","attributes":{},"color":"rgb(79,106,149)","size":1.0},{"source":"64","target":"10","id":"413","attributes":{},"color":"rgb(79,106,149)","size":1.0},{"source":"62","target":"64","id":"399","attributes":{},"color":"rgb(79,106,149)","size":1.0},{"source":"42","target":"5","id":"248","attributes":{},"color":"rgb(255,82,0)","size":1.0},{"source":"16","target":"19","id":"97","attributes":{},"color":"rgb(99,172,0)","size":1.0},{"source":"60","target":"52","id":"381","attributes":{},"color":"rgb(79,106,149)","size":1.0},{"source":"69","target":"9","id":"445","attributes":{},"color":"rgb(79,106,149)","size":1.0},{"source":"73","target":"37","id":"473","attributes":{},"color":"rgb(79,106,149)","size":1.0},{"source":"80","target":"9","id":"495","attributes":{},"color":"rgb(79,106,149)","size":1.0},{"source":"0","target":"68","id":"11","attributes":{},"color":"rgb(99,172,0)","size":1.0},{"source":"34","target":"22","id":"202","attributes":{},"color":"rgb(0,174,152)","size":1.0},{"source":"45","target":"19","id":"267","attributes":{},"color":"rgb(99,172,0)","size":1.0},{"source":"69","target":"49","id":"451","attributes":{},"color":"rgb(79,106,149)","size":1.0},{"source":"87","target":"73","id":"544","attributes":{},"color":"rgb(79,106,149)","size":1.0},{"source":"60","target":"27","id":"375","attributes":{},"color":"rgb(79,106,149)","size":1.0},{"source":"31","target":"19","id":"193","attributes":{},"color":"rgb(99,172,0)","size":1.0},{"source":"69","target":"52","id":"453","attributes":{},"color":"rgb(79,106,149)","size":1.0},{"source":"10","target":"80","id":"68","attributes":{},"color":"rgb(79,106,149)","size":1.0},{"source":"37","target":"87","id":"221","attributes":{},"color":"rgb(79,106,149)","size":1.0},{"source":"50","target":"31","id":"323","attributes":{},"color":"rgb(99,172,0)","size":1.0},{"source":"46","target":"27","id":"274","attributes":{},"color":"rgb(79,106,149)","size":1.0},{"source":"49","target":"87","id":"316","attributes":{},"color":"rgb(79,106,149)","size":1.0},{"source":"51","target":"52","id":"336","attributes":{},"color":"rgb(79,106,149)","size":1.0},{"source":"9","target":"83","id":"60","attributes":{},"color":"rgb(79,106,149)","size":1.0},{"source":"3","target":"33","id":"24","attributes":{},"color":"rgb(139,118,74)","size":1.0},{"source":"84","target":"85","id":"524","attributes":{},"color":"rgb(0,174,152)","size":1.0},{"source":"49","target":"30","id":"305","attributes":{},"color":"rgb(79,106,149)","size":1.0},{"source":"68","target":"50","id":"442","attributes":{},"color":"rgb(99,172,0)","size":1.0},{"source":"62","target":"80","id":"402","attributes":{},"color":"rgb(79,106,149)","size":1.0},{"source":"52","target":"51","id":"349","attributes":{},"color":"rgb(79,106,149)","size":1.0},{"source":"37","target":"69","id":"217","attributes":{},"color":"rgb(79,106,149)","size":1.0},{"source":"47","target":"18","id":"291","attributes":{},"color":"rgb(99,172,0)","size":1.0},{"source":"10","target":"64","id":"66","attributes":{},"color":"rgb(79,106,149)","size":1.0},{"source":"30","target":"27","id":"178","attributes":{},"color":"rgb(79,106,149)","size":1.0},{"source":"38","target":"69","id":"230","attributes":{},"color":"rgb(79,106,149)","size":1.0},{"source":"9","target":"27","id":"46","attributes":{},"color":"rgb(79,106,149)","size":1.0},{"source":"23","target":"16","id":"141","attributes":{},"color":"rgb(99,172,0)","size":1.0},{"source":"52","target":"64","id":"351","attributes":{},"color":"rgb(79,106,149)","size":1.0},{"source":"57","target":"74","id":"368","attributes":{},"color":"rgb(255,57,173)","size":1.0},{"source":"43","target":"75","id":"263","attributes":{},"color":"rgb(255,82,0)","size":1.0},{"source":"38","target":"46","id":"227","attributes":{},"color":"rgb(79,106,149)","size":1.0},{"source":"87","target":"3","id":"529","attributes":{},"color":"rgb(79,106,149)","size":1.0},{"source":"87","target":"27","id":"532","attributes":{},"color":"rgb(79,106,149)","size":1.0},{"source":"48","target":"73","id":"301","attributes":{},"color":"rgb(139,118,74)","size":1.0},{"source":"64","target":"73","id":"425","attributes":{},"color":"rgb(79,106,149)","size":1.0},{"source":"75","target":"43","id":"492","attributes":{},"color":"rgb(255,82,0)","size":1.0},{"source":"29","target":"72","id":"176","attributes":{},"color":"rgb(39,130,69)","size":1.0},{"source":"37","target":"30","id":"209","attributes":{},"color":"rgb(79,106,149)","size":1.0},{"source":"80","target":"69","id":"506","attributes":{},"color":"rgb(79,106,149)","size":1.0},{"source":"83","target":"49","id":"517","attributes":{},"color":"rgb(79,106,149)","size":1.0},{"source":"46","target":"51","id":"279","attributes":{},"color":"rgb(79,106,149)","size":1.0},{"source":"37","target":"38","id":"210","attributes":{},"color":"rgb(79,106,149)","size":1.0},{"source":"18","target":"13","id":"104","attributes":{},"color":"rgb(99,172,0)","size":1.0},{"source":"21","target":"14","id":"125","attributes":{},"color":"rgb(0,174,152)","size":1.0},{"source":"26","target":"14","id":"154","attributes":{},"color":"rgb(0,174,152)","size":1.0},{"source":"40","target":"63","id":"245","attributes":{},"color":"rgb(255,82,0)","size":1.0},{"source":"37","target":"80","id":"219","attributes":{},"color":"rgb(79,106,149)","size":1.0},{"source":"42","target":"70","id":"255","attributes":{},"color":"rgb(255,82,0)","size":1.0},{"source":"50","target":"39","id":"324","attributes":{},"color":"rgb(99,172,0)","size":1.0},{"source":"69","target":"3","id":"444","attributes":{},"color":"rgb(79,106,149)","size":1.0},{"source":"45","target":"47","id":"269","attributes":{},"color":"rgb(99,172,0)","size":1.0},{"source":"2","target":"5","id":"16","attributes":{},"color":"rgb(255,82,0)","size":1.0},{"source":"39","target":"13","id":"235","attributes":{},"color":"rgb(99,172,0)","size":1.0},{"source":"38","target":"30","id":"225","attributes":{},"color":"rgb(79,106,149)","size":1.0},{"source":"73","target":"30","id":"471","attributes":{},"color":"rgb(79,106,149)","size":1.0},{"source":"73","target":"49","id":"477","attributes":{},"color":"rgb(79,106,149)","size":1.0},{"source":"73","target":"64","id":"481","attributes":{},"color":"rgb(79,106,149)","size":1.0},{"source":"80","target":"38","id":"499","attributes":{},"color":"rgb(79,106,149)","size":1.0},{"source":"83","target":"9","id":"511","attributes":{},"color":"rgb(79,106,149)","size":1.0},{"source":"50","target":"54","id":"327","attributes":{},"color":"rgb(99,172,0)","size":1.0},{"source":"64","target":"80","id":"426","attributes":{},"color":"rgb(79,106,149)","size":1.0},{"source":"68","target":"45","id":"440","attributes":{},"color":"rgb(99,172,0)","size":1.0},{"source":"60","target":"69","id":"384","attributes":{},"color":"rgb(79,106,149)","size":1.0},{"source":"83","target":"87","id":"523","attributes":{},"color":"rgb(79,106,149)","size":1.0},{"source":"62","target":"27","id":"391","attributes":{},"color":"rgb(79,106,149)","size":1.0},{"source":"21","target":"67","id":"129","attributes":{},"color":"rgb(0,174,152)","size":1.0},{"source":"22","target":"21","id":"133","attributes":{},"color":"rgb(0,174,152)","size":1.0},{"source":"48","target":"3","id":"298","attributes":{},"color":"rgb(139,118,74)","size":1.0},{"source":"60","target":"49","id":"379","attributes":{},"color":"rgb(79,106,149)","size":1.0},{"source":"47","target":"16","id":"290","attributes":{},"color":"rgb(99,172,0)","size":1.0},{"source":"18","target":"16","id":"105","attributes":{},"color":"rgb(99,172,0)","size":1.0},{"source":"33","target":"3","id":"198","attributes":{},"color":"rgb(139,118,74)","size":1.0},{"source":"13","target":"19","id":"74","attributes":{},"color":"rgb(99,172,0)","size":1.0},{"source":"78","target":"56","id":"494","attributes":{},"color":"rgb(255,82,0)","size":1.0},{"source":"43","target":"70","id":"262","attributes":{},"color":"rgb(255,82,0)","size":1.0},{"source":"25","target":"5","id":"148","attributes":{},"color":"rgb(255,82,0)","size":1.0},{"source":"60","target":"87","id":"388","attributes":{},"color":"rgb(79,106,149)","size":1.0},{"source":"46","target":"60","id":"280","attributes":{},"color":"rgb(79,106,149)","size":1.0},{"source":"15","target":"5","id":"86","attributes":{},"color":"rgb(255,82,0)","size":1.0},{"source":"52","target":"49","id":"348","attributes":{},"color":"rgb(79,106,149)","size":1.0},{"source":"87","target":"62","id":"541","attributes":{},"color":"rgb(79,106,149)","size":1.0},{"source":"9","target":"62","id":"55","attributes":{},"color":"rgb(79,106,149)","size":1.0},{"source":"23","target":"39","id":"144","attributes":{},"color":"rgb(99,172,0)","size":1.0},{"source":"10","target":"83","id":"69","attributes":{},"color":"rgb(79,106,149)","size":1.0},{"source":"23","target":"50","id":"146","attributes":{},"color":"rgb(99,172,0)","size":1.0},{"source":"62","target":"46","id":"395","attributes":{},"color":"rgb(79,106,149)","size":1.0},{"source":"9","target":"60","id":"54","attributes":{},"color":"rgb(79,106,149)","size":1.0},{"source":"51","target":"80","id":"342","attributes":{},"color":"rgb(79,106,149)","size":1.0},{"source":"15","target":"70","id":"92","attributes":{},"color":"rgb(255,82,0)","size":1.0},{"source":"52","target":"30","id":"347","attributes":{},"color":"rgb(79,106,149)","size":1.0},{"source":"60","target":"46","id":"378","attributes":{},"color":"rgb(79,106,149)","size":1.0},{"source":"70","target":"63","id":"465","attributes":{},"color":"rgb(255,82,0)","size":1.0},{"source":"62","target":"49","id":"396","attributes":{},"color":"rgb(79,106,149)","size":1.0},{"source":"80","target":"73","id":"507","attributes":{},"color":"rgb(79,106,149)","size":1.0},{"source":"68","target":"54","id":"443","attributes":{},"color":"rgb(99,172,0)","size":1.0},{"source":"18","target":"54","id":"112","attributes":{},"color":"rgb(99,172,0)","size":1.0},{"source":"62","target":"83","id":"403","attributes":{},"color":"rgb(79,106,149)","size":1.0},{"source":"83","target":"69","id":"521","attributes":{},"color":"rgb(79,106,149)","size":1.0},{"source":"49","target":"69","id":"313","attributes":{},"color":"rgb(79,106,149)","size":1.0},{"source":"49","target":"73","id":"314","attributes":{},"color":"rgb(79,106,149)","size":1.0},{"source":"13","target":"50","id":"78","attributes":{},"color":"rgb(99,172,0)","size":1.0},{"source":"69","target":"46","id":"450","attributes":{},"color":"rgb(79,106,149)","size":1.0},{"source":"54","target":"47","id":"361","attributes":{},"color":"rgb(99,172,0)","size":1.0},{"source":"8","target":"26","id":"43","attributes":{},"color":"rgb(0,174,152)","size":1.0},{"source":"23","target":"0","id":"139","attributes":{},"color":"rgb(99,172,0)","size":1.0},{"source":"34","target":"85","id":"203","attributes":{},"color":"rgb(0,174,152)","size":1.0},{"source":"50","target":"47","id":"326","attributes":{},"color":"rgb(99,172,0)","size":1.0},{"source":"60","target":"83","id":"387","attributes":{},"color":"rgb(79,106,149)","size":1.0},{"source":"73","target":"46","id":"475","attributes":{},"color":"rgb(79,106,149)","size":1.0},{"source":"47","target":"45","id":"294","attributes":{},"color":"rgb(99,172,0)","size":1.0},{"source":"18","target":"50","id":"111","attributes":{},"color":"rgb(99,172,0)","size":1.0},{"source":"45","target":"18","id":"266","attributes":{},"color":"rgb(99,172,0)","size":1.0},{"source":"38","target":"80","id":"232","attributes":{},"color":"rgb(79,106,149)","size":1.0},{"source":"58","target":"82","id":"369","attributes":{},"color":"rgb(173,73,93)","size":1.0},{"source":"22","target":"85","id":"138","attributes":{},"color":"rgb(0,174,152)","size":1.0},{"source":"46","target":"37","id":"276","attributes":{},"color":"rgb(79,106,149)","size":1.0},{"source":"52","target":"80","id":"353","attributes":{},"color":"rgb(79,106,149)","size":1.0},{"source":"47","target":"68","id":"297","attributes":{},"color":"rgb(99,172,0)","size":1.0},{"source":"27","target":"38","id":"162","attributes":{},"color":"rgb(79,106,149)","size":1.0},{"source":"3","target":"9","id":"23","attributes":{},"color":"rgb(79,106,149)","size":1.0},{"source":"19","target":"68","id":"124","attributes":{},"color":"rgb(99,172,0)","size":1.0},{"source":"46","target":"69","id":"283","attributes":{},"color":"rgb(79,106,149)","size":1.0},{"source":"73","target":"10","id":"469","attributes":{},"color":"rgb(79,106,149)","size":1.0},{"source":"64","target":"52","id":"421","attributes":{},"color":"rgb(79,106,149)","size":1.0},{"source":"68","target":"39","id":"439","attributes":{},"color":"rgb(99,172,0)","size":1.0},{"source":"75","target":"15","id":"491","attributes":{},"color":"rgb(255,82,0)","size":1.0},{"source":"38","target":"3","id":"222","attributes":{},"color":"rgb(79,106,149)","size":1.0},{"source":"30","target":"37","id":"179","attributes":{},"color":"rgb(79,106,149)","size":1.0},{"source":"60","target":"9","id":"374","attributes":{},"color":"rgb(79,106,149)","size":1.0},{"source":"23","target":"19","id":"143","attributes":{},"color":"rgb(99,172,0)","size":1.0},{"source":"51","target":"9","id":"329","attributes":{},"color":"rgb(79,106,149)","size":1.0},{"source":"60","target":"51","id":"380","attributes":{},"color":"rgb(79,106,149)","size":1.0},{"source":"25","target":"63","id":"150","attributes":{},"color":"rgb(255,82,0)","size":1.0},{"source":"26","target":"5","id":"152","attributes":{},"color":"rgb(127,128,76)","size":1.0},{"source":"69","target":"64","id":"456","attributes":{},"color":"rgb(79,106,149)","size":1.0},{"source":"9","target":"38","id":"49","attributes":{},"color":"rgb(79,106,149)","size":1.0},{"source":"23","target":"47","id":"145","attributes":{},"color":"rgb(99,172,0)","size":1.0},{"source":"37","target":"49","id":"212","attributes":{},"color":"rgb(79,106,149)","size":1.0},{"source":"46","target":"38","id":"277","attributes":{},"color":"rgb(79,106,149)","size":1.0},{"source":"59","target":"42","id":"372","attributes":{},"color":"rgb(255,82,0)","size":1.0},{"source":"80","target":"60","id":"503","attributes":{},"color":"rgb(79,106,149)","size":1.0},{"source":"27","target":"9","id":"159","attributes":{},"color":"rgb(79,106,149)","size":1.0},{"source":"5","target":"1","id":"31","attributes":{},"color":"rgb(255,82,0)","size":1.0},{"source":"48","target":"33","id":"300","attributes":{},"color":"rgb(199,131,0)","size":1.0},{"source":"37","target":"10","id":"207","attributes":{},"color":"rgb(79,106,149)","size":1.0},{"source":"87","target":"49","id":"538","attributes":{},"color":"rgb(79,106,149)","size":1.0},{"source":"46","target":"62","id":"281","attributes":{},"color":"rgb(79,106,149)","size":1.0},{"source":"15","target":"63","id":"91","attributes":{},"color":"rgb(255,82,0)","size":1.0},{"source":"30","target":"51","id":"183","attributes":{},"color":"rgb(79,106,149)","size":1.0},{"source":"43","target":"59","id":"260","attributes":{},"color":"rgb(255,82,0)","size":1.0},{"source":"69","target":"73","id":"457","attributes":{},"color":"rgb(79,106,149)","size":1.0},{"source":"16","target":"23","id":"98","attributes":{},"color":"rgb(99,172,0)","size":1.0},{"source":"87","target":"38","id":"536","attributes":{},"color":"rgb(79,106,149)","size":1.0},{"source":"3","target":"49","id":"28","attributes":{},"color":"rgb(79,106,149)","size":1.0},{"source":"16","target":"54","id":"102","attributes":{},"color":"rgb(99,172,0)","size":1.0},{"source":"16","target":"68","id":"103","attributes":{},"color":"rgb(99,172,0)","size":1.0},{"source":"51","target":"30","id":"332","attributes":{},"color":"rgb(79,106,149)","size":1.0},{"source":"2","target":"42","id":"18","attributes":{},"color":"rgb(255,82,0)","size":1.0},{"source":"83","target":"27","id":"513","attributes":{},"color":"rgb(79,106,149)","size":1.0},{"source":"43","target":"2","id":"256","attributes":{},"color":"rgb(255,82,0)","size":1.0},{"source":"70","target":"43","id":"464","attributes":{},"color":"rgb(255,82,0)","size":1.0},{"source":"13","target":"47","id":"77","attributes":{},"color":"rgb(99,172,0)","size":1.0},{"source":"30","target":"46","id":"181","attributes":{},"color":"rgb(79,106,149)","size":1.0},{"source":"37","target":"62","id":"215","attributes":{},"color":"rgb(79,106,149)","size":1.0},{"source":"80","target":"27","id":"497","attributes":{},"color":"rgb(79,106,149)","size":1.0},{"source":"5","target":"75","id":"39","attributes":{},"color":"rgb(255,82,0)","size":1.0},{"source":"85","target":"22","id":"526","attributes":{},"color":"rgb(0,174,152)","size":1.0},{"source":"42","target":"44","id":"253","attributes":{},"color":"rgb(255,82,0)","size":1.0},{"source":"19","target":"39","id":"120","attributes":{},"color":"rgb(99,172,0)","size":1.0},{"source":"75","target":"5","id":"489","attributes":{},"color":"rgb(255,82,0)","size":1.0},{"source":"50","target":"45","id":"325","attributes":{},"color":"rgb(99,172,0)","size":1.0},{"source":"14","target":"34","id":"83","attributes":{},"color":"rgb(0,174,152)","size":1.0},{"source":"49","target":"9","id":"303","attributes":{},"color":"rgb(79,106,149)","size":1.0},{"source":"68","target":"47","id":"441","attributes":{},"color":"rgb(99,172,0)","size":1.0},{"source":"50","target":"16","id":"319","attributes":{},"color":"rgb(99,172,0)","size":1.0},{"source":"15","target":"59","id":"90","attributes":{},"color":"rgb(255,82,0)","size":1.0},{"source":"64","target":"87","id":"427","attributes":{},"color":"rgb(79,106,149)","size":1.0},{"source":"68","target":"16","id":"436","attributes":{},"color":"rgb(99,172,0)","size":1.0},{"source":"18","target":"19","id":"106","attributes":{},"color":"rgb(99,172,0)","size":1.0},{"source":"62","target":"69","id":"400","attributes":{},"color":"rgb(79,106,149)","size":1.0},{"source":"51","target":"27","id":"331","attributes":{},"color":"rgb(79,106,149)","size":1.0},{"source":"39","target":"19","id":"238","attributes":{},"color":"rgb(99,172,0)","size":1.0},{"source":"27","target":"51","id":"165","attributes":{},"color":"rgb(79,106,149)","size":1.0},{"source":"30","target":"83","id":"190","attributes":{},"color":"rgb(79,106,149)","size":1.0},{"source":"55","target":"86","id":"364","attributes":{},"color":"rgb(0,191,246)","size":1.0},{"source":"43","target":"41","id":"258","attributes":{},"color":"rgb(255,82,0)","size":1.0},{"source":"21","target":"85","id":"130","attributes":{},"color":"rgb(0,174,152)","size":1.0},{"source":"22","target":"8","id":"132","attributes":{},"color":"rgb(0,174,152)","size":1.0},{"source":"22","target":"26","id":"135","attributes":{},"color":"rgb(0,174,152)","size":1.0},{"source":"54","target":"0","id":"354","attributes":{},"color":"rgb(99,172,0)","size":1.0},{"source":"83","target":"73","id":"522","attributes":{},"color":"rgb(79,106,149)","size":1.0},{"source":"9","target":"51","id":"52","attributes":{},"color":"rgb(79,106,149)","size":1.0},{"source":"30","target":"52","id":"184","attributes":{},"color":"rgb(79,106,149)","size":1.0},{"source":"70","target":"15","id":"462","attributes":{},"color":"rgb(255,82,0)","size":1.0},{"source":"67","target":"22","id":"434","attributes":{},"color":"rgb(0,174,152)","size":1.0},{"source":"9","target":"64","id":"56","attributes":{},"color":"rgb(79,106,149)","size":1.0},{"source":"60","target":"64","id":"383","attributes":{},"color":"rgb(79,106,149)","size":1.0},{"source":"8","target":"22","id":"42","attributes":{},"color":"rgb(0,174,152)","size":1.0},{"source":"32","target":"48","id":"196","attributes":{},"color":"rgb(199,131,0)","size":1.0},{"source":"87","target":"10","id":"531","attributes":{},"color":"rgb(79,106,149)","size":1.0},{"source":"49","target":"51","id":"308","attributes":{},"color":"rgb(79,106,149)","size":1.0},{"source":"63","target":"40","id":"408","attributes":{},"color":"rgb(255,82,0)","size":1.0},{"source":"69","target":"38","id":"449","attributes":{},"color":"rgb(79,106,149)","size":1.0},{"source":"47","target":"54","id":"296","attributes":{},"color":"rgb(99,172,0)","size":1.0},{"source":"19","target":"45","id":"121","attributes":{},"color":"rgb(99,172,0)","size":1.0},{"source":"13","target":"16","id":"72","attributes":{},"color":"rgb(99,172,0)","size":1.0},{"source":"37","target":"46","id":"211","attributes":{},"color":"rgb(79,106,149)","size":1.0},{"source":"27","target":"46","id":"163","attributes":{},"color":"rgb(79,106,149)","size":1.0},{"source":"38","target":"62","id":"228","attributes":{},"color":"rgb(79,106,149)","size":1.0},{"source":"31","target":"0","id":"192","attributes":{},"color":"rgb(99,172,0)","size":1.0},{"source":"16","target":"47","id":"100","attributes":{},"color":"rgb(99,172,0)","size":1.0},{"source":"27","target":"73","id":"171","attributes":{},"color":"rgb(79,106,149)","size":1.0},{"source":"0","target":"54","id":"10","attributes":{},"color":"rgb(99,172,0)","size":1.0},{"source":"23","target":"54","id":"147","attributes":{},"color":"rgb(99,172,0)","size":1.0},{"source":"3","target":"48","id":"27","attributes":{},"color":"rgb(139,118,74)","size":1.0},{"source":"2","target":"59","id":"20","attributes":{},"color":"rgb(255,82,0)","size":1.0},{"source":"47","target":"23","id":"292","attributes":{},"color":"rgb(99,172,0)","size":1.0},{"source":"54","target":"13","id":"355","attributes":{},"color":"rgb(99,172,0)","size":1.0},{"source":"82","target":"58","id":"510","attributes":{},"color":"rgb(173,73,93)","size":1.0},{"source":"69","target":"27","id":"446","attributes":{},"color":"rgb(79,106,149)","size":1.0},{"source":"36","target":"42","id":"204","attributes":{},"color":"rgb(255,82,0)","size":1.0},{"source":"0","target":"23","id":"4","attributes":{},"color":"rgb(99,172,0)","size":1.0},{"source":"49","target":"60","id":"310","attributes":{},"color":"rgb(79,106,149)","size":1.0},{"source":"62","target":"38","id":"394","attributes":{},"color":"rgb(79,106,149)","size":1.0},{"source":"45","target":"68","id":"271","attributes":{},"color":"rgb(99,172,0)","size":1.0},{"source":"3","target":"37","id":"25","attributes":{},"color":"rgb(79,106,149)","size":1.0},{"source":"54","target":"50","id":"362","attributes":{},"color":"rgb(99,172,0)","size":1.0},{"source":"26","target":"1","id":"151","attributes":{},"color":"rgb(127,128,76)","size":1.0},{"source":"27","target":"49","id":"164","attributes":{},"color":"rgb(79,106,149)","size":1.0},{"source":"85","target":"21","id":"525","attributes":{},"color":"rgb(0,174,152)","size":1.0},{"source":"60","target":"37","id":"377","attributes":{},"color":"rgb(79,106,149)","size":1.0},{"source":"27","target":"69","id":"170","attributes":{},"color":"rgb(79,106,149)","size":1.0},{"source":"45","target":"39","id":"268","attributes":{},"color":"rgb(99,172,0)","size":1.0},{"source":"85","target":"84","id":"527","attributes":{},"color":"rgb(0,174,152)","size":1.0},{"source":"62","target":"73","id":"401","attributes":{},"color":"rgb(79,106,149)","size":1.0},{"source":"1","target":"5","id":"12","attributes":{},"color":"rgb(255,82,0)","size":1.0},{"source":"69","target":"87","id":"460","attributes":{},"color":"rgb(79,106,149)","size":1.0},{"source":"27","target":"64","id":"169","attributes":{},"color":"rgb(79,106,149)","size":1.0},{"source":"0","target":"45","id":"7","attributes":{},"color":"rgb(99,172,0)","size":1.0},{"source":"87","target":"80","id":"545","attributes":{},"color":"rgb(79,106,149)","size":1.0},{"source":"25","target":"56","id":"149","attributes":{},"color":"rgb(255,82,0)","size":1.0},{"source":"87","target":"60","id":"540","attributes":{},"color":"rgb(79,106,149)","size":1.0},{"source":"37","target":"73","id":"218","attributes":{},"color":"rgb(79,106,149)","size":1.0},{"source":"45","target":"0","id":"265","attributes":{},"color":"rgb(99,172,0)","size":1.0},{"source":"28","target":"87","id":"175","attributes":{},"color":"rgb(79,106,149)","size":1.0},{"source":"68","target":"19","id":"438","attributes":{},"color":"rgb(99,172,0)","size":1.0},{"source":"68","target":"18","id":"437","attributes":{},"color":"rgb(99,172,0)","size":1.0},{"source":"51","target":"37","id":"333","attributes":{},"color":"rgb(79,106,149)","size":1.0},{"source":"60","target":"30","id":"376","attributes":{},"color":"rgb(79,106,149)","size":1.0},{"source":"9","target":"73","id":"58","attributes":{},"color":"rgb(79,106,149)","size":1.0},{"source":"19","target":"54","id":"123","attributes":{},"color":"rgb(99,172,0)","size":1.0},{"source":"72","target":"29","id":"466","attributes":{},"color":"rgb(39,130,69)","size":1.0},{"source":"15","target":"43","id":"89","attributes":{},"color":"rgb(255,82,0)","size":1.0},{"source":"73","target":"48","id":"476","attributes":{},"color":"rgb(139,118,74)","size":1.0},{"source":"87","target":"9","id":"530","attributes":{},"color":"rgb(79,106,149)","size":1.0},{"source":"73","target":"83","id":"484","attributes":{},"color":"rgb(79,106,149)","size":1.0},{"source":"10","target":"73","id":"67","attributes":{},"color":"rgb(79,106,149)","size":1.0},{"source":"27","target":"60","id":"167","attributes":{},"color":"rgb(79,106,149)","size":1.0},{"source":"43","target":"42","id":"259","attributes":{},"color":"rgb(255,82,0)","size":1.0},{"source":"5","target":"25","id":"35","attributes":{},"color":"rgb(255,82,0)","size":1.0},{"source":"23","target":"13","id":"140","attributes":{},"color":"rgb(99,172,0)","size":1.0},{"source":"42","target":"15","id":"250","attributes":{},"color":"rgb(255,82,0)","size":1.0},{"source":"19","target":"0","id":"114","attributes":{},"color":"rgb(99,172,0)","size":1.0},{"source":"30","target":"9","id":"177","attributes":{},"color":"rgb(79,106,149)","size":1.0},{"source":"87","target":"69","id":"543","attributes":{},"color":"rgb(79,106,149)","size":1.0},{"source":"62","target":"30","id":"392","attributes":{},"color":"rgb(79,106,149)","size":1.0},{"source":"18","target":"68","id":"113","attributes":{},"color":"rgb(99,172,0)","size":1.0},{"source":"54","target":"68","id":"363","attributes":{},"color":"rgb(99,172,0)","size":1.0},{"source":"73","target":"69","id":"482","attributes":{},"color":"rgb(79,106,149)","size":1.0},{"source":"83","target":"37","id":"515","attributes":{},"color":"rgb(79,106,149)","size":1.0},{"source":"27","target":"80","id":"172","attributes":{},"color":"rgb(79,106,149)","size":1.0},{"source":"30","target":"73","id":"189","attributes":{},"color":"rgb(79,106,149)","size":1.0},{"source":"70","target":"42","id":"463","attributes":{},"color":"rgb(255,82,0)","size":1.0},{"source":"38","target":"64","id":"229","attributes":{},"color":"rgb(79,106,149)","size":1.0},{"source":"2","target":"43","id":"19","attributes":{},"color":"rgb(255,82,0)","size":1.0},{"source":"21","target":"26","id":"127","attributes":{},"color":"rgb(0,174,152)","size":1.0},{"source":"83","target":"60","id":"519","attributes":{},"color":"rgb(79,106,149)","size":1.0},{"source":"19","target":"23","id":"118","attributes":{},"color":"rgb(99,172,0)","size":1.0},{"source":"60","target":"80","id":"386","attributes":{},"color":"rgb(79,106,149)","size":1.0},{"source":"51","target":"73","id":"341","attributes":{},"color":"rgb(79,106,149)","size":1.0},{"source":"80","target":"10","id":"496","attributes":{},"color":"rgb(79,106,149)","size":1.0},{"source":"18","target":"47","id":"110","attributes":{},"color":"rgb(99,172,0)","size":1.0},{"source":"9","target":"30","id":"47","attributes":{},"color":"rgb(79,106,149)","size":1.0},{"source":"14","target":"67","id":"84","attributes":{},"color":"rgb(0,174,152)","size":1.0},{"source":"80","target":"87","id":"508","attributes":{},"color":"rgb(79,106,149)","size":1.0},{"source":"63","target":"25","id":"407","attributes":{},"color":"rgb(255,82,0)","size":1.0},{"source":"52","target":"27","id":"346","attributes":{},"color":"rgb(79,106,149)","size":1.0},{"source":"41","target":"43","id":"246","attributes":{},"color":"rgb(255,82,0)","size":1.0},{"source":"54","target":"16","id":"356","attributes":{},"color":"rgb(99,172,0)","size":1.0},{"source":"63","target":"43","id":"409","attributes":{},"color":"rgb(255,82,0)","size":1.0},{"source":"64","target":"51","id":"420","attributes":{},"color":"rgb(79,106,149)","size":1.0},{"source":"22","target":"24","id":"134","attributes":{},"color":"rgb(0,174,152)","size":1.0},{"source":"65","target":"81","id":"430","attributes":{},"color":"rgb(255,57,173)","size":1.0},{"source":"34","target":"14","id":"200","attributes":{},"color":"rgb(0,174,152)","size":1.0},{"source":"9","target":"87","id":"61","attributes":{},"color":"rgb(79,106,149)","size":1.0},{"source":"69","target":"30","id":"447","attributes":{},"color":"rgb(79,106,149)","size":1.0},{"source":"83","target":"30","id":"514","attributes":{},"color":"rgb(79,106,149)","size":1.0},{"source":"64","target":"62","id":"423","attributes":{},"color":"rgb(79,106,149)","size":1.0},{"source":"5","target":"11","id":"33","attributes":{},"color":"rgb(255,82,0)","size":1.0},{"source":"54","target":"23","id":"359","attributes":{},"color":"rgb(99,172,0)","size":1.0},{"source":"65","target":"31","id":"428","attributes":{},"color":"rgb(177,114,86)","size":1.0},{"source":"69","target":"83","id":"459","attributes":{},"color":"rgb(79,106,149)","size":1.0},{"source":"22","target":"34","id":"136","attributes":{},"color":"rgb(0,174,152)","size":1.0},{"source":"42","target":"11","id":"249","attributes":{},"color":"rgb(255,82,0)","size":1.0},{"source":"39","target":"45","id":"240","attributes":{},"color":"rgb(99,172,0)","size":1.0},{"source":"81","target":"65","id":"509","attributes":{},"color":"rgb(255,57,173)","size":1.0},{"source":"13","target":"23","id":"75","attributes":{},"color":"rgb(99,172,0)","size":1.0},{"source":"13","target":"0","id":"71","attributes":{},"color":"rgb(99,172,0)","size":1.0},{"source":"57","target":"65","id":"367","attributes":{},"color":"rgb(255,57,173)","size":1.0},{"source":"37","target":"60","id":"214","attributes":{},"color":"rgb(79,106,149)","size":1.0},{"source":"39","target":"54","id":"243","attributes":{},"color":"rgb(99,172,0)","size":1.0},{"source":"46","target":"80","id":"285","attributes":{},"color":"rgb(79,106,149)","size":1.0},{"source":"42","target":"43","id":"252","attributes":{},"color":"rgb(255,82,0)","size":1.0},{"source":"30","target":"87","id":"191","attributes":{},"color":"rgb(79,106,149)","size":1.0},{"source":"54","target":"18","id":"357","attributes":{},"color":"rgb(99,172,0)","size":1.0},{"source":"63","target":"15","id":"406","attributes":{},"color":"rgb(255,82,0)","size":1.0},{"source":"69","target":"51","id":"452","attributes":{},"color":"rgb(79,106,149)","size":1.0},{"source":"73","target":"32","id":"472","attributes":{},"color":"rgb(139,118,74)","size":1.0},{"source":"49","target":"62","id":"311","attributes":{},"color":"rgb(79,106,149)","size":1.0},{"source":"52","target":"9","id":"345","attributes":{},"color":"rgb(79,106,149)","size":1.0},{"source":"67","target":"21","id":"433","attributes":{},"color":"rgb(0,174,152)","size":1.0},{"source":"5","target":"2","id":"32","attributes":{},"color":"rgb(255,82,0)","size":1.0},{"source":"16","target":"0","id":"94","attributes":{},"color":"rgb(99,172,0)","size":1.0},{"source":"26","target":"8","id":"153","attributes":{},"color":"rgb(0,174,152)","size":1.0},{"source":"0","target":"39","id":"6","attributes":{},"color":"rgb(99,172,0)","size":1.0},{"source":"19","target":"13","id":"115","attributes":{},"color":"rgb(99,172,0)","size":1.0},{"source":"73","target":"9","id":"468","attributes":{},"color":"rgb(79,106,149)","size":1.0},{"source":"63","target":"79","id":"411","attributes":{},"color":"rgb(255,82,0)","size":1.0},{"source":"46","target":"9","id":"272","attributes":{},"color":"rgb(79,106,149)","size":1.0},{"source":"38","target":"37","id":"226","attributes":{},"color":"rgb(79,106,149)","size":1.0},{"source":"50","target":"18","id":"320","attributes":{},"color":"rgb(99,172,0)","size":1.0},{"source":"2","target":"75","id":"22","attributes":{},"color":"rgb(255,82,0)","size":1.0},{"source":"80","target":"51","id":"501","attributes":{},"color":"rgb(79,106,149)","size":1.0},{"source":"1","target":"75","id":"15","attributes":{},"color":"rgb(255,82,0)","size":1.0},{"source":"2","target":"63","id":"21","attributes":{},"color":"rgb(255,82,0)","size":1.0},{"source":"64","target":"69","id":"424","attributes":{},"color":"rgb(79,106,149)","size":1.0},{"source":"49","target":"3","id":"302","attributes":{},"color":"rgb(79,106,149)","size":1.0},{"source":"49","target":"37","id":"306","attributes":{},"color":"rgb(79,106,149)","size":1.0},{"source":"54","target":"39","id":"360","attributes":{},"color":"rgb(99,172,0)","size":1.0},{"source":"23","target":"18","id":"142","attributes":{},"color":"rgb(99,172,0)","size":1.0},{"source":"70","target":"5","id":"461","attributes":{},"color":"rgb(255,82,0)","size":1.0},{"source":"83","target":"62","id":"520","attributes":{},"color":"rgb(79,106,149)","size":1.0},{"source":"87","target":"28","id":"533","attributes":{},"color":"rgb(79,106,149)","size":1.0},{"source":"30","target":"49","id":"182","attributes":{},"color":"rgb(79,106,149)","size":1.0},{"source":"51","target":"69","id":"340","attributes":{},"color":"rgb(79,106,149)","size":1.0},{"source":"27","target":"30","id":"160","attributes":{},"color":"rgb(79,106,149)","size":1.0},{"source":"38","target":"27","id":"224","attributes":{},"color":"rgb(79,106,149)","size":1.0},{"source":"44","target":"42","id":"264","attributes":{},"color":"rgb(255,82,0)","size":1.0},{"source":"5","target":"70","id":"38","attributes":{},"color":"rgb(255,82,0)","size":1.0},{"source":"73","target":"60","id":"479","attributes":{},"color":"rgb(79,106,149)","size":1.0},{"source":"16","target":"13","id":"95","attributes":{},"color":"rgb(99,172,0)","size":1.0},{"source":"42","target":"59","id":"254","attributes":{},"color":"rgb(255,82,0)","size":1.0},{"source":"67","target":"14","id":"432","attributes":{},"color":"rgb(0,174,152)","size":1.0},{"source":"3","target":"69","id":"29","attributes":{},"color":"rgb(79,106,149)","size":1.0},{"source":"46","target":"10","id":"273","attributes":{},"color":"rgb(79,106,149)","size":1.0},{"source":"5","target":"42","id":"37","attributes":{},"color":"rgb(255,82,0)","size":1.0},{"source":"69","target":"37","id":"448","attributes":{},"color":"rgb(79,106,149)","size":1.0},{"source":"62","target":"37","id":"393","attributes":{},"color":"rgb(79,106,149)","size":1.0},{"source":"83","target":"46","id":"516","attributes":{},"color":"rgb(79,106,149)","size":1.0},{"source":"6","target":"87","id":"40","attributes":{},"color":"rgb(79,106,149)","size":1.0},{"source":"87","target":"30","id":"534","attributes":{},"color":"rgb(79,106,149)","size":1.0},{"source":"51","target":"49","id":"335","attributes":{},"color":"rgb(79,106,149)","size":1.0},{"source":"73","target":"62","id":"480","attributes":{},"color":"rgb(79,106,149)","size":1.0},{"source":"9","target":"46","id":"50","attributes":{},"color":"rgb(79,106,149)","size":1.0},{"source":"18","target":"23","id":"107","attributes":{},"color":"rgb(99,172,0)","size":1.0},{"source":"86","target":"55","id":"528","attributes":{},"color":"rgb(0,191,246)","size":1.0},{"source":"10","target":"46","id":"63","attributes":{},"color":"rgb(79,106,149)","size":1.0},{"source":"1","target":"26","id":"14","attributes":{},"color":"rgb(127,128,76)","size":1.0},{"source":"3","target":"87","id":"30","attributes":{},"color":"rgb(79,106,149)","size":1.0},{"source":"80","target":"37","id":"498","attributes":{},"color":"rgb(79,106,149)","size":1.0},{"source":"39","target":"0","id":"234","attributes":{},"color":"rgb(99,172,0)","size":1.0},{"source":"59","target":"2","id":"370","attributes":{},"color":"rgb(255,82,0)","size":1.0},{"source":"64","target":"37","id":"416","attributes":{},"color":"rgb(79,106,149)","size":1.0},{"source":"65","target":"57","id":"429","attributes":{},"color":"rgb(255,57,173)","size":1.0},{"source":"37","target":"51","id":"213","attributes":{},"color":"rgb(79,106,149)","size":1.0},{"source":"15","target":"2","id":"85","attributes":{},"color":"rgb(255,82,0)","size":1.0},{"source":"80","target":"64","id":"505","attributes":{},"color":"rgb(79,106,149)","size":1.0},{"source":"9","target":"49","id":"51","attributes":{},"color":"rgb(79,106,149)","size":1.0}]}